ntfy_wrapper/__init__.py
ntfy_wrapper/cli.py
ntfy_wrapper/notifier.py
ntfy_wrapper/utils.py
ntfy_wrapper-0.1.7.dist-info/entry_points.txt
ntfy_wrapper-0.1.7.dist-info/LICENSE
ntfy_wrapper-0.1.7.dist-info/WHEEL
ntfy_wrapper-0.1.7.dist-info/METADATA
ntfy_wrapper-0.1.7.dist-info/RECORD
