Metadata-Version: 2.1
Name: ntfy-wrapper
Version: 0.1.7
Summary: Fast & Free notifications for your code: Python wrapper around the ntfy.sh notifications service.
License: MIT
Author: vict0rsch
Author-email: vsch@pm.me
Requires-Python: >=3.8,<4.0
Classifier: License :: OSI Approved :: MIT License
Classifier: Programming Language :: Python :: 3
Classifier: Programming Language :: Python :: 3.8
Classifier: Programming Language :: Python :: 3.9
Classifier: Programming Language :: Python :: 3.10
Classifier: Programming Language :: Python :: 3.11
Requires-Dist: requests (>=2.28.1,<3.0.0)
Requires-Dist: typer[all] (>=0.7.0,<0.8.0)
Requires-Dist: xkcdpass (>=1.19.3,<2.0.0)
